dmarc/__init__.py
dmarc/admin.py
dmarc/apps.py
dmarc/models.py
dmarc/test_import.py
dmarc/urls.py
dmarc/views.py
dmarc/__pycache__/__init__.cpython-36.pyc
dmarc/__pycache__/admin.cpython-36.pyc
dmarc/__pycache__/apps.cpython-36.pyc
dmarc/__pycache__/models.cpython-36.pyc
dmarc/__pycache__/urls.cpython-36.pyc
dmarc/__pycache__/views.cpython-36.pyc
dmarc/management/__init__.py
dmarc/management/__pycache__/__init__.cpython-36.pyc
dmarc/management/commands/__init__.py
dmarc/management/commands/importdmarcfeedback.py
dmarc/management/commands/importdmarcreport.py
dmarc/management/commands/__pycache__/__init__.cpython-36.pyc
dmarc/management/commands/__pycache__/importdmarcreport.cpython-36.pyc
dmarc/migrations/0001_initial.py
dmarc/migrations/__init__.py
dmarc/migrations/__pycache__/0001_initial.cpython-36.pyc
dmarc/migrations/__pycache__/__init__.cpython-36.pyc
dmarc/templates/admin/dmarc/app_index.html
dmarc/templates/dmarc/report.html
django_dmarc2-0.5.2.dist-info/AUTHORS
django_dmarc2-0.5.2.dist-info/LICENSE
django_dmarc2-0.5.2.dist-info/METADATA
django_dmarc2-0.5.2.dist-info/WHEEL
django_dmarc2-0.5.2.dist-info/top_level.txt
django_dmarc2-0.5.2.dist-info/RECORD
