Metadata-Version: 2.1
Name: django-dmarc2
Version: 0.5.2
Summary: Managing DMARC aggregate and feedback reports
Home-page: https://github.com/webtweakers/django-dmarc
Author: Alan Hicks
Author-email: ahicks@p-o.co.uk
License: BSD
Download-URL: https://pypi.python.org/pypi/django-dmarc2
Keywords: dmarc email spf dkim
Platform: UNKNOWN
Classifier: Development Status :: 4 - Beta
Classifier: Environment :: Web Environment
Classifier: Framework :: Django
Classifier: Framework :: Django :: 2.0
Classifier: Framework :: Django :: 2.1
Classifier: Framework :: Django :: 2.2
Classifier: Intended Audience :: Developers
Classifier: License :: OSI Approved :: BSD License
Classifier: Operating System :: OS Independent
Classifier: Programming Language :: Python :: 3
Classifier: Topic :: Internet :: WWW/HTTP
Classifier: Topic :: Office/Business
Classifier: Topic :: Software Development :: Libraries :: Python Modules
Requires: django
